README.rst
setup.cfg
setup.py
oaas_simple/__init__.py
oaas_simple/py.typed
oaas_simple.egg-info/PKG-INFO
oaas_simple.egg-info/SOURCES.txt
oaas_simple.egg-info/dependency_links.txt
oaas_simple.egg-info/requires.txt
oaas_simple.egg-info/top_level.txt
oaas_simple/client/__init__.py
oaas_simple/client/client.py
oaas_simple/client/service_client_proxy.py
oaas_simple/client/single_method.py
oaas_simple/data/__init__.py
oaas_simple/registry/__init__.py
oaas_simple/registry/__main__.py
oaas_simple/registry/local_registry.py
oaas_simple/rpc/__init__.py
oaas_simple/rpc/call_pb2.py
oaas_simple/rpc/call_pb2_grpc.py
oaas_simple/server/__init__.py
oaas_simple/server/server.py
oaas_simple/server/service_invoker_proxy.py
test/__init__.py